pts_isospi_control/__init__.py
pts_isospi_control/isoSPIinterface.dbc
pts_isospi_control/isospi_interface.py
pts_isospi_control-0.0.8.dist-info/METADATA
pts_isospi_control-0.0.8.dist-info/WHEEL
pts_isospi_control-0.0.8.dist-info/top_level.txt
pts_isospi_control-0.0.8.dist-info/RECORD
