Metadata-Version: 2.1
Name: pts-isospi-control
Version: 0.0.8
Summary: Controls the PTS ISO SPI Interface
Home-page: https://gitlab.com/pass-testing-solutions/pts-isospi-interface-control
Author: Pass Testing Solutions GmbH
Author-email: info@pass-testing.de
License: MIT
Platform: UNKNOWN
Classifier: License :: OSI Approved :: MIT License
Classifier: Programming Language :: Python :: 3
Classifier: Programming Language :: Python :: 3.9
Requires-Dist: python-can
Requires-Dist: cantools
Requires-Dist: tabulate
